djtools/__init__.py
djtools/contact/__init__.py
djtools/contact/admin.py
djtools/contact/apps.py
djtools/contact/context_processors.py
djtools/contact/forms.py
djtools/contact/models.py
djtools/contact/services.py
djtools/contact/views.py
djtools/contact/locale/en/LC_MESSAGES/django.mo
djtools/contact/locale/en/LC_MESSAGES/django.po
djtools/contact/locale/es/LC_MESSAGES/django.mo
djtools/contact/locale/es/LC_MESSAGES/django.po
djtools/contact/locale/eu/LC_MESSAGES/django.mo
djtools/contact/locale/eu/LC_MESSAGES/django.po
djtools/contact/migrations/0001_initial.py
djtools/contact/migrations/__init__.py
djtools/contact/templates/djtools/contact/contactrequest_email.txt
djtools/contact/templates/djtools/contact/contactrequest_form.html
djtools/contact/templates/djtools/contact/google_maps.html
django_tools_contact-1.3.2.dist-info/LICENSE
django_tools_contact-1.3.2.dist-info/METADATA
django_tools_contact-1.3.2.dist-info/WHEEL
django_tools_contact-1.3.2.dist-info/top_level.txt
django_tools_contact-1.3.2.dist-info/RECORD
