Metadata-Version: 2.1
Name: django-tools-contact
Version: 1.3.2
Summary: A simple Django app to manage company contact information.
Home-page: UNKNOWN
Author: Toni Colom
Author-email: toni@semicolom.com
License: UNKNOWN
Platform: UNKNOWN
Classifier: Environment :: Web Environment
Classifier: Framework :: Django
Classifier: Framework :: Django :: 2.0
Classifier: Intended Audience :: Developers
Classifier: Operating System :: OS Independent
Classifier: Programming Language :: Python
Classifier: Programming Language :: Python :: 3.6
Classifier: Topic :: Internet :: WWW/HTTP
Classifier: Topic :: Internet :: WWW/HTTP :: Dynamic Content
Requires-Dist: django-recaptcha
